bulldog/__init__.py
bulldog/model.py
bulldog-1.0.3.dist-info/METADATA
bulldog-1.0.3.dist-info/RECORD
bulldog-1.0.3.dist-info/WHEEL
bulldog-1.0.3.dist-info/top_level.txt
