Metadata-Version: 2.1
Name: bulldog
Version: 1.0.3
Summary: State management for Data Science & Analytics
Home-page: https://github.com/luke14free/bulldog
Author: Luca Giacomel
Author-email: luca.giacomel@gmail.com
License: UNKNOWN
Platform: UNKNOWN
Classifier: Programming Language :: Python :: 3
Classifier: License :: OSI Approved :: MIT License
Classifier: Operating System :: OS Independent
Requires-Python: >=3.6
Requires-Dist: pathos
